malachi/__init__.py
malachi-1.0.3.dist-info/METADATA
malachi-1.0.3.dist-info/WHEEL
malachi-1.0.3.dist-info/top_level.txt
malachi-1.0.3.dist-info/RECORD
