Metadata-Version: 2.2
Name: malachi
Version: 1.0.3
Summary: A Python module for Windows 10 toast notifications
Home-page: https://github.com/lordskyzw/malachi
Author: Tarmica Chiwara
Author-email: tarimicac@gmail.com
Classifier: Programming Language :: Python :: 3
Classifier: License :: OSI Approved :: MIT License
Classifier: Operating System :: Microsoft :: Windows
Requires-Python: >=3.6
Requires-Dist: pywin32
Dynamic: author
Dynamic: author-email
Dynamic: classifier
Dynamic: description
Dynamic: description-content-type
Dynamic: home-page
Dynamic: requires-dist
Dynamic: requires-python
Dynamic: summary
